{
"#*": "{*}",
"#-N": "{PLOVER:ADD_TRANSLATION}",
"STPH": "{^}{>}",
"STPH-R": "{#Left}{^}",
"STPH-RB": "{#Control_L(Left)}{^}",
"STPH-RBG": "{#Control_L(Shift_L(Left))}",
"STPH-P": "{#Up}{^}",
"STPH-B": "{#Down}{^}",
"STPH-BG": "{#Control_L(Right)}{^}",
"STPH-G": "{#Right}{^}",
"SKVRAEURBGS": "{^\n\n^}{-|}",
"SKVRAURBGS": "{^\n\n^}{-|}",
"SKV-BGS": "{#Return}{^}",
"SH-FT": "{PLOVER:SWITCH_SYSTEM:English Stenotype}",
"SR-RS": "{#Control_L(End)}{^}",
"TKA/TO*": "{:time: %d/%B. %Y.}",
"TK*EL": "{#Delete}",
"TKUPT": "{PLOVER:ADD_TRANSLATION}",
"TK-FP": "{*!}",
"TK-FPS": "{*!}",
"TPV-R": "{#Alt_L(Left)}",
"TPV-G": "{#Alt_L(Right)}",
"TPEFBG": "{#Escape}",
"TA*B": "{#Tab}{^}",
"TA*BT": "{#Alt_L(Tab Tab)}",
"T*EUD": "{:time:%H:%M}",
"KPH*F": "{#Super_L(v)}",
"KPH*BG": "{#Super_L(k)}",
"KPH*T": "{#Super_L(w)}",
"KPH-BG": "{#Super_L(c)}",
"KPA": "{*-|}",
"KPA*": "{*>}",
"KPA*L": "{<}",
"KHR*U": "{#Control_L(u)}",
"KHR-F": "{#Control_L(f)}",
"KHR-BG": "{#Control_L(k)}",
"KRA*PL": "{MODE:RESET}",
"KRAPL": "{MODE:CAPS}",
"PV*FP": "{#BackSpace}",
"PV-FP": "{#BackSpace}",
"PHRO*F": "{PLOVER:SUSPEND}",
"PHRO*PB": "{PLOVER:RESUME}",
"PHROLG": "{PLOVER:TOGGLE}",
"R-R": "{#Return}{^}",
"A*FP": "{*?}",
"AFP": "{*?}"
}
